{
  "genesis_time": "2025-11-24T09:05:15Z",
  "chain_id": "sultan-1",
  "initial_height": "1",
  "consensus_params": {
    "block": {
      "max_bytes": "22020096",
      "max_gas": "-1",
      "time_iota_ms": "2000"
    },
    "evidence": {
      "max_age_num_blocks": "100000",
      "max_age_duration": "172800000000000"
    },
    "validator": {
      "pub_key_types": ["ed25519"]
    }
  },
  "validators": [
    {
      "address": "sultan1validator1933ee28148dc2bc9bc862d7488d5a21e4",
      "pub_key": {
        "type": "tendermint/PubKeyEd25519",
        "value": "xACd/eFtLR6fd14tyHmIzEV+N3hlEaUYPkvuaERbSEw="
      },
      "power": "10000000000000",
      "name": "genesis-validator-1"
    }
    ,
    {
      "address": "sultan1validator2ed4a1f647349315859e9fcfca321ed7de",
      "pub_key": {
        "type": "tendermint/PubKeyEd25519",
        "value": "Q6q7EE484VX/E6inTmnIK7Hj6vCLYvcr+k5GeZXrxuE="
      },
      "power": "10000000000000",
      "name": "genesis-validator-2"
    }
    ,
    {
      "address": "sultan1validator37b1ba9ca57cb2855402c3c9594f9df653",
      "pub_key": {
        "type": "tendermint/PubKeyEd25519",
        "value": "DKLzgyjofyebqe1GI9wRkybCYYjMfxshOacXJO52k1E="
      },
      "power": "10000000000000",
      "name": "genesis-validator-3"
    }
    ,
    {
      "address": "sultan1validator6439f3cc4df6ebaaeb6fffb80cb2dc790e",
      "pub_key": {
        "type": "tendermint/PubKeyEd25519",
        "value": "uwxZdtClZKkFTGUYv1mFR+b/4UsoW1r3zY3rMdhpD8E="
      },
      "power": "10000000000000",
      "name": "genesis-validator-4"
    }
    ,
    {
      "address": "sultan1validatorb0c419c918ea8126a205ecfb3430b0a64b",
      "pub_key": {
        "type": "tendermint/PubKeyEd25519",
        "value": "dOWT+ya7ouIhcOgSavmAf3wdty3ojifImPNaGZcdzpA="
      },
      "power": "10000000000000",
      "name": "genesis-validator-5"
    }
  ],
  "app_state": {
    "staking": {
      "validators": [
  {
    "validator_id": 1,
    "name": "genesis-validator-1",
    "address": "sultan1validator1933ee28148dc2bc9bc862d7488d5a21e4",
    "stake": "10000000000000",
    "commission": 0.0910158,
    "moniker": "Sultan Genesis Validator #1",
    "website": "https://sultanchain.io/validators/1",
    "details": "Genesis validator for Sultan L1 mainnet",
    "created_at": 1763975115
  },
  {
    "validator_id": 2,
    "name": "genesis-validator-2",
    "address": "sultan1validator2ed4a1f647349315859e9fcfca321ed7de",
    "stake": "10000000000000",
    "commission": 0.0910158,
    "moniker": "Sultan Genesis Validator #2",
    "website": "https://sultanchain.io/validators/2",
    "details": "Genesis validator for Sultan L1 mainnet",
    "created_at": 1763975115
  },
  {
    "validator_id": 3,
    "name": "genesis-validator-3",
    "address": "sultan1validator37b1ba9ca57cb2855402c3c9594f9df653",
    "stake": "10000000000000",
    "commission": 0.0910158,
    "moniker": "Sultan Genesis Validator #3",
    "website": "https://sultanchain.io/validators/3",
    "details": "Genesis validator for Sultan L1 mainnet",
    "created_at": 1763975115
  },
  {
    "validator_id": 4,
    "name": "genesis-validator-4",
    "address": "sultan1validator6439f3cc4df6ebaaeb6fffb80cb2dc790e",
    "stake": "10000000000000",
    "commission": 0.0910158,
    "moniker": "Sultan Genesis Validator #4",
    "website": "https://sultanchain.io/validators/4",
    "details": "Genesis validator for Sultan L1 mainnet",
    "created_at": 1763975115
  },
  {
    "validator_id": 5,
    "name": "genesis-validator-5",
    "address": "sultan1validatorb0c419c918ea8126a205ecfb3430b0a64b",
    "stake": "10000000000000",
    "commission": 0.0910158,
    "moniker": "Sultan Genesis Validator #5",
    "website": "https://sultanchain.io/validators/5",
    "details": "Genesis validator for Sultan L1 mainnet",
    "created_at": 1763975115
  }
]
    },
    "bank": {
      "total_supply": "500000000000000000",
      "balances": [
        {
          "address": "sultan1validator1933ee28148dc2bc9bc862d7488d5a21e4",
          "coins": [
            {
              "denom": "usltn",
              "amount": "50000000000000000"
            }
          ]
        }
        ,
        {
          "address": "sultan1validator2ed4a1f647349315859e9fcfca321ed7de",
          "coins": [
            {
              "denom": "usltn",
              "amount": "50000000000000000"
            }
          ]
        }
        ,
        {
          "address": "sultan1validator37b1ba9ca57cb2855402c3c9594f9df653",
          "coins": [
            {
              "denom": "usltn",
              "amount": "50000000000000000"
            }
          ]
        }
        ,
        {
          "address": "sultan1validator6439f3cc4df6ebaaeb6fffb80cb2dc790e",
          "coins": [
            {
              "denom": "usltn",
              "amount": "50000000000000000"
            }
          ]
        }
        ,
        {
          "address": "sultan1validatorb0c419c918ea8126a205ecfb3430b0a64b",
          "coins": [
            {
              "denom": "usltn",
              "amount": "50000000000000000"
            }
          ]
        }
      ]
    },
    "governance": {
      "starting_proposal_id": "1",
      "deposit_params": {
        "min_deposit": [
          {
            "denom": "usltn",
            "amount": "1000000000000"
          }
        ],
        "max_deposit_period": "604800000000000"
      },
      "voting_params": {
        "voting_period": "100800"
      },
      "tally_params": {
        "quorum": "0.334",
        "threshold": "0.5",
        "veto_threshold": "0.334"
      }
    },
    "economics": {
      "inflation_rate": 0.08,
      "validator_apy": 0.2667,
      "block_time": 2,
      "blocks_per_year": 15768000
    },
    "sharding": {
      "enabled": true,
      "shard_count": 100,
      "tx_per_shard": 10000
    }
  }
}
